[
    {
        "template": "qml",
        "platform": "x86_64",
        "language": "Python",
        "source": "openfaas",
        "description": "Quantum ML Template",
        "repo": "https://github.com/ibarabasi/templates",
        "official": "false"
    },
    {
        "template": "qasm",
        "platform": "x86_64",
        "language": "Python",
        "source": "openfaas",
        "description": "QASM on QC Simulator Template",
        "repo": "https://github.com/ibarabasi/templates",
        "official": "false"
    }
]
